jax_radio_tools/__init__.py
jax_radio_tools/coordinate_transformations.py
jax_radio_tools/jax_utils.py
jax_radio_tools/shower_utils.py
jax_radio_tools/trace_utils.py
jax_radio_tools/units.py
jax_radio_tools/atmosphere/__init__.py
jax_radio_tools/atmosphere/atm_models.py
jax_radio_tools/atmosphere/atmosphere.py
jax_radio_tools/atmosphere/gdas_model.py
jax_radio_tools-0.1.3.dist-info/licenses/LICENSE
jax_radio_tools-0.1.3.dist-info/METADATA
jax_radio_tools-0.1.3.dist-info/WHEEL
jax_radio_tools-0.1.3.dist-info/top_level.txt
jax_radio_tools-0.1.3.dist-info/RECORD
