Metadata-Version: 2.4
Name: jax_radio_tools
Version: 0.1.3
Summary: Tools used for radio emission of air showers in the JAX framework
Author-email: Keito Watanabe <keito.watanabe@kit.edu>
Classifier: Programming Language :: Python :: 3
Classifier: License :: OSI Approved :: GNU General Public License v3 (GPLv3)
Classifier: Operating System :: OS Independent
License-File: LICENSE
Requires-Dist: numpy>=1.20
Requires-Dist: jax
Requires-Dist: jaxlib
Requires-Dist: typing_extensions
Dynamic: license-file
